pynetbox_api/__init__.py
pynetbox_api/cache.py
pynetbox_api/database.py
pynetbox_api/exceptions.py
pynetbox_api/main.py
pynetbox_api/session.py
pynetbox_api/utils.py
pynetbox_api/api/__init__.py
pynetbox_api/api/routes/__init__.py
pynetbox_api/api/routes/dcim.py
pynetbox_api/api/routes/extras.py
pynetbox_api/api/routes/virtualization.py
pynetbox_api/dcim/__init__.py
pynetbox_api/dcim/device.py
pynetbox_api/dcim/device_role.py
pynetbox_api/dcim/device_type.py
pynetbox_api/dcim/interface.py
pynetbox_api/dcim/manufacturer.py
pynetbox_api/dcim/platform.py
pynetbox_api/dcim/site.py
pynetbox_api/extras/__init__.py
pynetbox_api/extras/custom_field.py
pynetbox_api/extras/tag.py
pynetbox_api/ipam/__init__.py
pynetbox_api/ipam/ip_address.py
pynetbox_api/virtualization/__init__.py
pynetbox_api/virtualization/cluster.py
pynetbox_api/virtualization/cluster_group.py
pynetbox_api/virtualization/cluster_type.py
pynetbox_api/virtualization/interface.py
pynetbox_api/virtualization/virtual_disk.py
pynetbox_api/virtualization/virtual_machine.py
pynetbox_api-0.0.2.post1.dist-info/licenses/LICENSE
pynetbox_api-0.0.2.post1.dist-info/METADATA
pynetbox_api-0.0.2.post1.dist-info/WHEEL
pynetbox_api-0.0.2.post1.dist-info/top_level.txt
pynetbox_api-0.0.2.post1.dist-info/RECORD
