Metadata-Version: 2.4
Name: pynetbox-api
Version: 0.0.2.post1
Summary: pynetbox API
Requires-Python: >=3.10
License-File: LICENSE
Requires-Dist: aiohttp>=3.11.11
Requires-Dist: fastapi[standard]
Requires-Dist: pydantic>=2.10.6
Requires-Dist: pynetbox>=7.4.1
Requires-Dist: python-dotenv>=1.0.1
Requires-Dist: requests>=2.32.3
Requires-Dist: sqlmodel>=0.0.22
Requires-Dist: typer>=0.15.1
Dynamic: license-file
